multiflash/__init__.py
multiflash/__main__.py
multiflash/common.py
multiflash/dataset.py
multiflash/gui.py
multiflash/question.py
multiflash/quiz.py
multiflash/tests/__init__.py
multiflash/tests/__main__.py
multiflash/tests/common.py
multiflash-0.4.0.dist-info/LICENSE
multiflash-0.4.0.dist-info/METADATA
multiflash-0.4.0.dist-info/WHEEL
multiflash-0.4.0.dist-info/entry_points.txt
multiflash-0.4.0.dist-info/top_level.txt
multiflash-0.4.0.dist-info/RECORD
