Metadata-Version: 2.1
Name: multiflash
Version: 0.4.0
Summary: study aid
Home-page: https://github.com/jreese/multiflash
Author: John Reese
Author-email: john@noswap.com
License: MIT
Platform: UNKNOWN
Classifier: License :: OSI Approved :: MIT License
Classifier: Programming Language :: Python
Classifier: Programming Language :: Python :: 3
Requires-Python: >=3.7
Requires-Dist: appdirs
Requires-Dist: aql
Requires-Dist: attrs
Requires-Dist: click
Requires-Dist: PySide2
